AUTHORS
CHANGELOG
LICENSE
MANIFEST.in
README.md
setup.py
bin/ica
iscowalive/__init__.py
iscowalive/ica.py
iscowalive.egg-info/PKG-INFO
iscowalive.egg-info/SOURCES.txt
iscowalive.egg-info/dependency_links.txt
iscowalive.egg-info/requires.txt
iscowalive.egg-info/top_level.txt