Metadata-Version: 1.0
Name: iscowalive
Version: 0.1
Summary: simple module that checks if url is available.
Home-page: https://github.com/cowlab/iscowalive
Author: Óscar M. Lage
Author-email: info@oscarmlage.com
License: BSD
Platform: UNKNOWN
